rt_utils/__init__.py
rt_utils/ds_helper.py
rt_utils/image_helper.py
rt_utils/rtstruct.py
rt_utils/rtstruct_builder.py
rt_utils/utils.py
tests/__init__.py
tests/conftest.py
tests/test_ds_helper.py
tests/test_rtstruct_builder.py
tests/test_utils.py
rt_utils-1.2.7.dist-info/LICENSE
rt_utils-1.2.7.dist-info/METADATA
rt_utils-1.2.7.dist-info/WHEEL
rt_utils-1.2.7.dist-info/top_level.txt
rt_utils-1.2.7.dist-info/RECORD
